fileren/files_renamer.py
fileren/functions.py
fileren/main.py
fileren-0.3.0.dist-info/entry_points.txt
fileren-0.3.0.dist-info/LICENSE
fileren-0.3.0.dist-info/WHEEL
fileren-0.3.0.dist-info/METADATA
fileren-0.3.0.dist-info/RECORD
