Metadata-Version: 2.1
Name: fileren
Version: 0.3.0
Summary: Simple tool for renaming files in a directory
Author: Mikołaj Badyl
Author-email: contact@hawier.dev
Requires-Python: >=3.7,<4.0
Classifier: Programming Language :: Python :: 3
Classifier: Programming Language :: Python :: 3.7
Classifier: Programming Language :: Python :: 3.8
Classifier: Programming Language :: Python :: 3.9
Classifier: Programming Language :: Python :: 3.10
Requires-Dist: rich (>=12.6.0,<13.0.0)
